13-async-up-counter-4bit/verilog/async_counter_4bit.v
`timescale 1ns/1ps

// ============================================================
// T Flip-Flop — Negative edge triggered, toggle mode
// ============================================================
module tff (
    input  clk,
    input  reset,   // active HIGH async reset
    output reg q
);
    always @(negedge clk or posedge reset) begin
        if (reset) q <= 0;
        else       q <= ~q;
    end
endmodule


// ============================================================
// 4-bit Asynchronous Ripple Counter
// Each FF output drives the clock of the next — ripple effect
// Equivalent to 7493 IC configuration
// ============================================================
module async_counter_4bit (
    input  clk,
    input  reset,
    output wire [3:0] q
);
    // QA clocked by external clk
    // QB clocked by QA
    // QC clocked by QB
    // QD clocked by QC
    tff ff0 (.clk(clk  ), .reset(reset), .q(q[0]));
    tff ff1 (.clk(q[0] ), .reset(reset), .q(q[1]));
    tff ff2 (.clk(q[1] ), .reset(reset), .q(q[2]));
    tff ff3 (.clk(q[2] ), .reset(reset), .q(q[3]));

endmodule

Implementation of 4 bit Asynchronous Up Counter/Verilog/tb.v
`timescale 1ns/1ps

module tb_async_counter;

    reg  clk, reset;
    wire [3:0] q;

    async_counter_4bit uut (
        .clk   (clk  ),
        .reset (reset),
        .q     (q    )
    );

    // Clock: 20ns period
    initial clk = 0;
    always #10 clk = ~clk;

    // VCD dump — dumps all internal FF signals too
    initial begin
        $dumpfile("async_counter.vcd");
        $dumpvars(0, tb_async_counter);
    end

    initial begin
        // Reset
        reset = 1; #25;
        reset = 0;

        $display("");
        $display(" | QD  QC  QB  QA | Decimal");
        $display("-----------------------------");

        repeat(17) begin
            @(negedge clk); #2;
            $display(" |  %b   %b   %b   %b  |   %0d",
                      q[3], q[2], q[1], q[0], q);
        end

        $display("-------------------------------");
        $display("");

        // Run 2 full cycles for clean GTKWave view
        repeat(32) @(negedge clk);

        $display("Done. Open async_counter.vcd in GTKWave.");
        $finish;
    end

endmodule

Implementation of 4 bit Asynchronous Up Counter/Verilog/async_counter.vcd
$date
	Fri May 01 01:50:34 2026
$end
$version
	Icarus Verilog
$end
$timescale
	1ps
$end
$scope module tb_async_counter $end
$var wire 4 ! q [3:0] $end
$var reg 1 " clk $end
$var reg 1 # reset $end
$scope module uut $end
$var wire 1 " clk $end
$var wire 1 # reset $end
$var wire 4 $ q [3:0] $end
$scope module ff0 $end
$var wire 1 " clk $end
$var wire 1 # reset $end
$var reg 1 % q $end
$upscope $end
$scope module ff1 $end
$var wire 1 & clk $end
$var wire 1 # reset $end
$var reg 1 ' q $end
$upscope $end
$scope module ff2 $end
$var wire 1 ( clk $end
$var wire 1 # reset $end
$var reg 1 ) q $end
$upscope $end
$scope module ff3 $end
$var wire 1 * clk $end
$var wire 1 # reset $end
$var reg 1 + q $end
$upscope $end
$upscope $end
$upscope $end
$enddefinitions $end
$comment Show the parameter values. $end
$dumpall
$end
#0
$dumpvars
0+
0*
0)
0(
0'
0&
0%
b0 $
1#
0"
b0 !
$end
#10000
1"
#20000
0"
#25000
0#
#30000
1"
#40000
1&
b1 !
b1 $
1%
0"
#50000
1"
#60000
1(
1'
0&
b10 !
b10 $
0%
0"
#70000
1"
#80000
1&
b11 !
b11 $
1%
0"
#90000
1"
#100000
1*
1)
0(
0'
0&
b100 !
b100 $
0%
0"
#110000
1"
#120000
1&
b101 !
b101 $
1%
0"
#130000
1"
#140000
1(
1'
0&
b110 !
b110 $
0%
0"
#150000
1"
#160000
1&
b111 !
b111 $
1%
0"
#170000
1"
#180000
1+
0*
0)
0(
0'
0&
b1000 !
b1000 $
0%
0"
#190000
1"
#200000
1&
b1001 !
b1001 $
1%
0"
#210000
1"
#220000
1(
1'
0&
b1010 !
b1010 $
0%
0"
#230000
1"
#240000
1&
b1011 !
b1011 $
1%
0"
#250000
1"
#260000
1*
1)
0(
0'
0&
b1100 !
b1100 $
0%
0"
#270000
1"
#280000
1&
b1101 !
b1101 $
1%
0"
#290000
1"
#300000
1(
1'
0&
b1110 !
b1110 $
0%
0"
#310000
1"
#320000
1&
b1111 !
b1111 $
1%
0"
#330000
1"
#340000
0+
0*
0)
0(
0'
0&
b0 !
b0 $
0%
0"
#350000
1"
#360000
1&
b1 !
b1 $
1%
0"
#370000
1"
#380000
1(
1'
0&
b10 !
b10 $
0%
0"
#390000
1"
#400000
1&
b11 !
b11 $
1%
0"
#410000
1"
#420000
1*
1)
0(
0'
0&
b100 !
b100 $
0%
0"
#430000
1"
#440000
1&
b101 !
b101 $
1%
0"
#450000
1"
#460000
1(
1'
0&
b110 !
b110 $
0%
0"
#470000
1"
#480000
1&
b111 !
b111 $
1%
0"
#490000
1"
#500000
1+
0*
0)
0(
0'
0&
b1000 !
b1000 $
0%
0"
#510000
1"
#520000
1&
b1001 !
b1001 $
1%
0"
#530000
1"
#540000
1(
1'
0&
b1010 !
b1010 $
0%
0"
#550000
1"
#560000
1&
b1011 !
b1011 $
1%
0"
#570000
1"
#580000
1*
1)
0(
0'
0&
b1100 !
b1100 $
0%
0"
#590000
1"
#600000
1&
b1101 !
b1101 $
1%
0"
#610000
1"
#620000
1(
1'
0&
b1110 !
b1110 $
0%
0"
#630000
1"
#640000
1&
b1111 !
b1111 $
1%
0"
#650000
1"
#660000
0+
0*
0)
0(
0'
0&
b0 !
b0 $
0%
0"
#670000
1"
#680000
1&
b1 !
b1 $
1%
0"
#690000
1"
#700000
1(
1'
0&
b10 !
b10 $
0%
0"
#710000
1"
#720000
1&
b11 !
b11 $
1%
0"
#730000
1"
#740000
1*
1)
0(
0'
0&
b100 !
b100 $
0%
0"
#750000
1"
#760000
1&
b101 !
b101 $
1%
0"
#770000
1"
#780000
1(
1'
0&
b110 !
b110 $
0%
0"
#790000
1"
#800000
1&
b111 !
b111 $
1%
0"
#810000
1"
#820000
1+
0*
0)
0(
0'
0&
b1000 !
b1000 $
0%
0"
#830000
1"
#840000
1&
b1001 !
b1001 $
1%
0"
#850000
1"
#860000
1(
1'
0&
b1010 !
b1010 $
0%
0"
#870000
1"
#880000
1&
b1011 !
b1011 $
1%
0"
#890000
1"
#900000
1*
1)
0(
0'
0&
b1100 !
b1100 $
0%
0"
#910000
1"
#920000
1&
b1101 !
b1101 $
1%
0"
#930000
1"
#940000
1(
1'
0&
b1110 !
b1110 $
0%
0"
#950000
1"
#960000
1&
b1111 !
b1111 $
1%
0"
#970000
1"
#980000
0+
0*
0)
0(
0'
0&
b0 !
b0 $
0%
0"
#990000
1"
#1000000
1&
b1 !
b1 $
1%
0"
