Adder and Subtractor/Verilog/Adder/adder.v
module adder (
input A,B,C,
output sum_half,carry_half,
output sum_full,carry_full
);

//Half Adder
assign sum_half = A ^ B; //XOR gate
assign carry_half = A & B; //AND gate

//Full Adder
assign sum_full = A ^ B ^ C; //XOR gate
assign carry_full = (A & B) | (B & C) | (C & A); //Carry out using AND and OR gates


endmodule

Adder and Subtractor/Verilog/Adder/tb.v
`timescale 1ns / 1ps
module adder_tb;

    // Inputs
    reg A, B, C;

    // Outputs
    wire sum_half, carry_half;
    wire sum_full, carry_full;

    // Clock
    reg clk;

    // Instantiate DUT
    adder uut (
        .A(A),
        .B(B),
        .C(C),
        .sum_half(sum_half),
        .carry_half(carry_half),
        .sum_full(sum_full),
        .carry_full(carry_full)
    );

    // Clock generation for random inputs
    initial clk = 0;
    always #5 clk = ~clk;

    // Dump waveform for GTKWave from the start
    initial begin
        $dumpfile("waveform.vcd");
        $dumpvars(0, adder_tb);
    end

    // --------------------------
    // Part 1: Manual test vectors
    // --------------------------
    initial begin
        C = 0;

        $display("---- Half Adder ----");
        $display("A B | sumH carryH");
        A=0; B=0; #10; $display("%b %b | %b %b", A,B,sum_half,carry_half);
        A=0; B=1; #10; $display("%b %b | %b %b", A,B,sum_half,carry_half);
        A=1; B=0; #10; $display("%b %b | %b %b", A,B,sum_half,carry_half);
        A=1; B=1; #10; $display("%b %b | %b %b", A,B,sum_half,carry_half);

        $display("\n---- Full Adder ----");
        $display("A B C | sumH carryH | sumF carryF");
        A=0; B=0; C=0; #10; $display("%b %b %b | %b %b | %b %b", A,B,C,sum_half,carry_half,sum_full,carry_full);
        A=0; B=0; C=1; #10; $display("%b %b %b | %b %b | %b %b", A,B,C,sum_half,carry_half,sum_full,carry_full);
        A=0; B=1; C=0; #10; $display("%b %b %b | %b %b | %b %b", A,B,C,sum_half,carry_half,sum_full,carry_full);
        A=0; B=1; C=1; #10; $display("%b %b %b | %b %b | %b %b", A,B,C,sum_half,carry_half,sum_full,carry_full);
        A=1; B=0; C=0; #10; $display("%b %b %b | %b %b | %b %b", A,B,C,sum_half,carry_half,sum_full,carry_full);
        A=1; B=0; C=1; #10; $display("%b %b %b | %b %b | %b %b", A,B,C,sum_half,carry_half,sum_full,carry_full);
        A=1; B=1; C=0; #10; $display("%b %b %b | %b %b | %b %b", A,B,C,sum_half,carry_half,sum_full,carry_full);
        A=1; B=1; C=1; #10; $display("%b %b %b | %b %b | %b %b", A,B,C,sum_half,carry_half,sum_full,carry_full);
    end

    // --------------------------
    // Part 2: Random inputs
    // --------------------------
    // Only after the manual vectors (delay to avoid overlap)
    initial begin
        #100; // wait for manual vectors to finish
        forever @(posedge clk) begin
            A <= $random & 1;
            B <= $random & 1;
            C <= $random & 1;
        end
    end



    // Stop simulation after enough time for both parts
    initial begin
        #300 $finish;
    end

endmodule

Adder and Subtractor/Verilog/Adder/waveform.vcd
$date
	Sat Feb 07 02:19:07 2026
$end
$version
	Icarus Verilog
$end
$timescale
	1ps
$end
$scope module adder_tb $end
$var wire 1 ! sum_half $end
$var wire 1 " sum_full $end
$var wire 1 # carry_half $end
$var wire 1 $ carry_full $end
$var reg 1 % A $end
$var reg 1 & B $end
$var reg 1 ' C $end
$var reg 1 ( clk $end
$scope module uut $end
$var wire 1 % A $end
$var wire 1 & B $end
$var wire 1 ' C $end
$var wire 1 $ carry_full $end
$var wire 1 # carry_half $end
$var wire 1 " sum_full $end
$var wire 1 ! sum_half $end
$upscope $end
$upscope $end
$enddefinitions $end
$comment Show the parameter values. $end
$dumpall
$end
#0
$dumpvars
0(
0'
0&
0%
0$
0#
0"
0!
$end
#5000
1(
#10000
1"
1!
0(
1&
#15000
1(
#20000
0(
0&
1%
#25000
1(
#30000
1$
0"
0!
1#
0(
1&
#35000
1(
#40000
0$
0#
0(
0&
0%
#45000
1(
#50000
1"
0(
1'
#55000
1(
#60000
1!
0(
0'
1&
#65000
1(
#70000
1$
0"
0(
1'
#75000
1(
#80000
0$
1"
0(
0'
0&
1%
#85000
1(
#90000
1$
0"
0(
1'
#95000
1(
#100000
0!
1#
0(
0'
1&
#105000
1!
0#
1'
0%
1(
#110000
1"
0!
1#
0(
1%
#115000
1(
#120000
0(
#125000
0"
1!
0#
0&
1(
#130000
0(
#135000
1(
#140000
0(
#145000
1(
#150000
0(
#155000
0$
1"
0'
1&
0%
1(
#160000
0(
#165000
1$
0"
0!
1#
1%
1(
#170000
0(
#175000
0$
1"
1!
0#
0&
1(
#180000
0(
#185000
1&
0%
1(
#190000
0(
#195000
1$
0!
1#
1'
1%
1(
#200000
0(
#205000
0$
1!
0#
0'
0&
1(
#210000
0(
#215000
0!
1'
0%
1(
#220000
0(
#225000
1$
0"
1!
1&
1(
#230000
0(
#235000
1"
0!
1#
1%
1(
#240000
0(
#245000
0$
0#
0&
0%
1(
#250000
0(
#255000
1$
0"
1#
0'
1&
1%
1(
#260000
0(
#265000
0$
0#
0&
0%
1(
#270000
0(
#275000
1"
1!
1&
1(
#280000
0(
#285000
1$
0"
1'
1(
#290000
0(
#295000
0$
0!
0'
0&
1(
