11-jk-master-slave-flip-flop/verilog/jk_ms_ff.v
`timescale 1ns/1ps

// ============================================================
// JK Master-Slave Flip-Flop — Gate-Level Structural Model
// Equivalent to 7476 IC behavior
// Trigger: Falling edge of CLK
// PRE_bar / CLR_bar: Active LOW asynchronous override
// ============================================================

module jk_ms_ff (
    input  j,
    input  k,
    input  clk,
    input  pre_bar,   // Active LOW async preset  — forces Q=1
    input  clr_bar,   // Active LOW async clear   — forces Q=0
    output q,
    output q_bar
);

    wire clk_bar;
    wire m1, m2;
    wire s_s, r_s;
    wire s1, s2;

    // Clock inversion — slave is active when clk_bar=1
    not  #1 CLK_bar (clk_bar, clk);

    // Master steering gates — feedback from slave output (q, q_bar)
    nand #1 g3m (m1, j, q_bar, clk);
    nand #1 g4m (m2, k, q,     clk);

    // Master SR latch — pre/clr included to break x on startup
    nand #1 g1m (s_s, m1, r_s, pre_bar);
    nand #1 g2m (r_s, m2, s_s, clr_bar);

    // Slave steering gates — active only when clk_bar=1 (CLK=0)
    nand #1 g3s (s1, s_s, clk_bar);
    nand #1 g4s (s2, r_s, clk_bar);

    // Slave SR latch — true async pre/clr override at output
    nand #1 g1s (q,     s1, q_bar, pre_bar);
    nand #1 g2s (q_bar, s2, q,     clr_bar);

endmodule

Master Slave J-K Flip Flop/Verilog/tb.v
`timescale 1ns/1ps

module tb_jk_ms_ff;

    reg  j, k, clk;
    reg  pre_bar, clr_bar;
    wire q, q_bar;

    jk_ms_ff uut (
        .j       (j      ),
        .k       (k      ),
        .clk     (clk    ),
        .pre_bar (pre_bar),
        .clr_bar (clr_bar),
        .q       (q      ),
        .q_bar   (q_bar  )
    );

    // Clock: 20ns period
    initial clk = 0;
    always #10 clk = ~clk;

    // VCD dump for GTKWave
    initial begin
        $dumpfile("jk_ms_ff.vcd");
        $dumpvars(0, tb_jk_ms_ff);
    end

    // --------------------------------------------------------
    // Truth Table
    // --------------------------------------------------------
    initial begin
        pre_bar = 1; clr_bar = 1; j = 0; k = 0;

        // Hold clr_bar low for full clock cycle to flush x from both latches
        clr_bar = 0; #30; clr_bar = 1;
        #10;
        @(negedge clk);

        $display("");
        $display("  J  K  |  Q    Q_bar  | Operation");
        $display("--------------------------------------");

        // HOLD (Q was 0)
        j=0; k=0; @(negedge clk); #2;
        $display("  %b  %b  |  %b      %b    | HOLD", j, k, q, q_bar);

        // SET
        j=1; k=0; @(negedge clk); #2;
        $display("  %b  %b  |  %b      %b    | SET", j, k, q, q_bar);

        // HOLD (Q was 1)
        j=0; k=0; @(negedge clk); #2;
        $display("  %b  %b  |  %b      %b    | HOLD", j, k, q, q_bar);

        // RESET
        j=0; k=1; @(negedge clk); #2;
        $display("  %b  %b  |  %b      %b    | RESET", j, k, q, q_bar);

        // TOGGLE (0 → 1)
        j=1; k=1; @(negedge clk); #2;
        $display("  %b  %b  |  %b      %b    | TOGGLE", j, k, q, q_bar);

        // TOGGLE (1 → 0)
        j=1; k=1; @(negedge clk); #2;
        $display("  %b  %b  |  %b      %b    | TOGGLE", j, k, q, q_bar);

        $display("--------------------------------------");
        $display("");

        // Async PRE test
        pre_bar = 0; #15;
        $display("  PRE_bar=0 → Q=%b  Q_bar=%b  (expect Q=1)", q, q_bar);
        pre_bar = 1; #20;

        // Async CLR test
        clr_bar = 0; #15;
        $display("  CLR_bar=0 → Q=%b  Q_bar=%b  (expect Q=0)", q, q_bar);
        clr_bar = 1;
        $display("");
    end

    // --------------------------------------------------------
    // Random Sequence for GTKWave
    // --------------------------------------------------------
    integer seed = 42;
    integer i;

    initial begin
        #400;

        $display("  J  K  |  Q    Q_bar  | (random sequence)");
        $display("--------------------------------------");

        for (i = 0; i < 20; i = i + 1) begin
            @(posedge clk);
            j = $random(seed) % 2;
            k = $random(seed) % 2;
            @(negedge clk); #2;
            $display("  %b  %b  |  %b      %b    |", j, k, q, q_bar);
        end

        $display("--------------------------------------");
        $display("Done. Open jk_ms_ff.vcd in GTKWave.");
        $finish;
    end

endmodule

Master Slave J-K Flip Flop/Verilog/jk_ms_ff.vcd
$date
	Wed Apr 29 01:12:47 2026
$end
$version
	Icarus Verilog
$end
$timescale
	1ps
$end
$scope module tb_jk_ms_ff $end
$var wire 1 ! q_bar $end
$var wire 1 " q $end
$var reg 1 # clk $end
$var reg 1 $ clr_bar $end
$var reg 1 % j $end
$var reg 1 & k $end
$var reg 1 ' pre_bar $end
$var integer 32 ( i [31:0] $end
$var integer 32 ) seed [31:0] $end
$scope module uut $end
$var wire 1 # clk $end
$var wire 1 * clk_bar $end
$var wire 1 $ clr_bar $end
$var wire 1 % j $end
$var wire 1 & k $end
$var wire 1 + m1 $end
$var wire 1 , m2 $end
$var wire 1 ' pre_bar $end
$var wire 1 " q $end
$var wire 1 ! q_bar $end
$var wire 1 - r_s $end
$var wire 1 . s1 $end
$var wire 1 / s2 $end
$var wire 1 0 s_s $end
$upscope $end
$upscope $end
$enddefinitions $end
$comment Show the parameter values. $end
$dumpall
$end
#0
$dumpvars
x0
x/
x.
x-
x,
x+
x*
b101010 )
bx (
1'
0&
0%
0$
0#
x"
x!
$end
#1000
1*
1!
1-
1,
1+
#2000
0/
00
#3000
1.
#4000
0"
#10000
1#
#11000
0*
#12000
1/
#20000
0#
#21000
1*
#22000
0/
#30000
1#
1$
#31000
0*
#32000
1/
#40000
0#
#41000
1*
#42000
0/
#50000
1#
#51000
0*
#52000
1/
#60000
0#
#61000
1*
#62000
0/
1%
#70000
1#
#71000
0*
0+
#72000
1/
10
#73000
0-
#80000
0#
#81000
1*
1+
#82000
0.
0%
#83000
1"
#84000
0!
#90000
1#
#91000
0*
#92000
1.
#100000
0#
#101000
1*
#102000
0.
1&
#110000
1#
#111000
0*
0,
#112000
1.
1-
#113000
00
#120000
0#
#121000
1*
1,
#122000
0/
1%
#123000
1!
#124000
0"
#130000
1#
#131000
0*
0+
#132000
1/
10
#133000
0-
#140000
0#
#141000
1*
1+
#142000
0.
#143000
1"
#144000
0!
#150000
1#
#151000
0*
0,
#152000
1.
1-
#153000
00
#160000
0#
#161000
1*
1,
#162000
0/
0'
#163000
1!
10
#164000
0-
0.
#165000
1/
#166000
0!
#170000
1#
#171000
0*
0,
#172000
1.
1-
#177000
1'
#178000
00
#180000
0#
#181000
1*
1,
#182000
0/
#183000
1!
#184000
0"
#190000
1#
#191000
0*
0+
#192000
1/
10
#193000
0-
#197000
0$
#198000
1-
#200000
0#
#201000
1*
1+
#202000
0.
0/
00
#203000
1"
1.
#204000
0"
#210000
1#
#211000
0*
0+
#212000
1/
10
1$
#213000
0-
#220000
0#
#221000
1*
1+
#222000
0.
#223000
1"
#224000
0!
#230000
1#
#231000
0*
0,
#232000
1.
1-
#233000
00
#240000
0#
#241000
1*
1,
#242000
0/
#243000
1!
#244000
0"
#250000
1#
#251000
0*
0+
#252000
1/
10
#253000
0-
#260000
0#
#261000
1*
1+
#262000
0.
#263000
1"
#264000
0!
#270000
1#
#271000
0*
0,
#272000
1.
1-
#273000
00
#280000
0#
#281000
1*
1,
#282000
0/
#283000
1!
#284000
0"
#290000
1#
#291000
0*
0+
#292000
1/
10
#293000
0-
#300000
0#
#301000
1*
1+
#302000
0.
#303000
1"
#304000
0!
#310000
1#
#311000
0*
0,
#312000
1.
1-
#313000
00
#320000
0#
#321000
1*
1,
#322000
0/
#323000
1!
#324000
0"
#330000
1#
#331000
0*
0+
#332000
1/
10
#333000
0-
#340000
0#
#341000
1*
1+
#342000
0.
#343000
1"
#344000
0!
#350000
1#
#351000
0*
0,
#352000
1.
1-
#353000
00
#360000
0#
#361000
1*
1,
#362000
0/
#363000
1!
#364000
0"
#370000
1#
#371000
0*
0+
#372000
1/
10
#373000
0-
#380000
0#
#381000
1*
1+
#382000
0.
#383000
1"
#384000
0!
#390000
1#
#391000
0*
0,
#392000
1.
1-
#393000
00
#400000
0#
b0 (
#401000
1*
1,
#402000
0/
#403000
1!
#404000
0"
#410000
0%
b10100110100001000111000010001000 )
1#
#411000
0*
#412000
1/
#420000
0#
#421000
1*
#422000
0/
b1 (
#430000
b1000101110101011100001110010110 )
1#
#431000
0*
#432000
1/
#440000
0#
#441000
1*
#442000
0/
b10 (
#450000
1%
b1011010111101001000010011010100 )
1#
#451000
0*
0+
#452000
1/
10
#453000
0-
#460000
0#
#461000
1*
1+
#462000
0.
b11 (
#463000
1"
#464000
0!
#470000
0&
0%
b11111010001000000101111000010 )
1#
#471000
0*
#472000
1.
#480000
0#
#481000
1*
#482000
0.
b100 (
#490000
1%
b10100010000000100101101111100000 )
1#
#491000
0*
#492000
1.
#500000
0#
#501000
1*
#502000
0.
b101 (
#510000
1&
0%
b11101101110110000010010101110 )
1#
#511000
0*
0,
#512000
1.
1-
#513000
00
#520000
0#
#521000
1*
1,
#522000
0/
b110 (
#523000
1!
#524000
0"
#530000
1%
b10011010111011010000000110101100 )
1#
#531000
0*
0+
#532000
1/
10
#533000
0-
#540000
0#
#541000
1*
1+
#542000
0.
b111 (
#543000
1"
#544000
0!
#550000
b1110001110110111001101001011010 )
1#
#551000
0*
0,
#552000
1.
1-
#553000
00
#560000
0#
#561000
1*
1,
#562000
0/
b1000 (
#563000
1!
#564000
0"
#570000
0&
0%
b1011100010000100100001000111000 )
1#
#571000
0*
#572000
1/
#580000
0#
#581000
1*
#582000
0/
b1001 (
#590000
1%
b110100011000110111100011000110 )
1#
#591000
0*
0+
#592000
1/
10
#593000
0-
#600000
0#
#601000
1*
1+
#602000
0.
b1010 (
#603000
1"
#604000
0!
#610000
1&
b1101001101010101010100110000100 )
1#
#611000
0*
0,
#612000
1.
1-
#613000
00
#620000
0#
#621000
1*
1,
#622000
0/
b1011 (
#623000
1!
#624000
0"
#630000
b1001011110110010000101111110010 )
1#
#631000
0*
0+
#632000
1/
10
#633000
0-
#640000
0#
#641000
1*
1+
#642000
0.
b1100 (
#643000
1"
#644000
0!
#650000
0&
0%
b11000100011101011000001110010000 )
1#
#651000
0*
#652000
1.
#660000
0#
#661000
1*
#662000
0.
b1101 (
#670000
1&
b10011010111101110111111111011110 )
1#
#671000
0*
0,
#672000
1.
1-
#673000
00
#680000
0#
#681000
1*
1,
#682000
0/
b1110 (
#683000
1!
#684000
0"
#690000
1%
b100010111001001101110001011100 )
1#
#691000
0*
0+
#692000
1/
10
#693000
0-
#700000
0#
#701000
1*
1+
#702000
0.
b1111 (
#703000
1"
#704000
0!
#710000
b11100011110110101100000010001010 )
1#
#711000
0*
0,
#712000
1.
1-
#713000
00
#720000
0#
#721000
1*
1,
#722000
0/
b10000 (
#723000
1!
#724000
0"
#730000
0&
0%
b10011010001110010111111111101000 )
1#
#731000
0*
#732000
1/
#740000
0#
#741000
1*
#742000
0/
b10001 (
#750000
1&
b10001011111010110111100111110110 )
1#
#751000
0*
#752000
1/
#760000
0#
#761000
1*
#762000
0/
b10010 (
#770000
0&
1%
b11000111011111101111101000110100 )
1#
#771000
0*
0+
#772000
1/
10
#773000
0-
#780000
0#
#781000
1*
1+
#782000
0.
b10011 (
#783000
1"
#784000
0!
#790000
1&
b101100100010110001100000100010 )
1#
#791000
0*
0,
#792000
1.
1-
#793000
00
#800000
0#
#801000
1*
1,
#802000
0/
b10100 (
