4 to 2 Priority Encoder/Verilog/4_to_2_priority_Encoder.v

module priority_encoder_4to2 (
  input [3:0] D,
  output reg [1:0] Y,
  output V
);

assign V = |D;   // capital V matches output

always @(*) begin

   if(D[3])
   Y = 2'b11;
   else if (D[2])
   Y = 2'b10;
   else if (D[1])
   Y = 2'b01;
   else if (D[0])
   Y= 2'b00;
   else
   Y = 2'b00;
end

endmodule

4 to 2 Priority Encoder/Verilog/tb.v
`timescale 1ns / 1ps

module priority_encoder_4to2_tb;

    // Inputs
    reg [3:0] D;

    // Outputs
    wire [1:0] Y;
    wire V;

    // Instantiate DUT
    priority_encoder_4to2 uut (
        .D(D),
        .Y(Y),
        .V(V)
    );

    // Dump waveform
    initial begin
        $dumpfile("waveform.vcd");
        $dumpvars(0, priority_encoder_4to2_tb);
    end

    // --------------------------
    // Part 1: Manual test vectors
    // --------------------------
    initial begin
        $display("---- 4 to 2 Priority Encoder ----");
        $display("D    | Y  V");

        D = 4'b0000; #10; $display("%b | %b %b", D,Y,V);
        D = 4'b0001; #10; $display("%b | %b %b", D,Y,V);
        D = 4'b0010; #10; $display("%b | %b %b", D,Y,V);
        D = 4'b0100; #10; $display("%b | %b %b", D,Y,V);
        D = 4'b1000; #10; $display("%b | %b %b", D,Y,V);
        D = 4'b1111; #10; $display("%b | %b %b", D,Y,V);
    end

    // --------------------------
    // Part 2: Random inputs
    // --------------------------
    initial begin
        #80;  // wait for manual part

        repeat (20) begin
            D = $random % 16;
            #10;
        end
    end

    // Stop simulation
    initial begin
        #300 $finish;
    end

endmodule

4 to 2 Priority Encoder/Verilog/waveform.vcd
$date
	Mon Feb 16 19:23:00 2026
$end
$version
	Icarus Verilog
$end
$timescale
	1ps
$end
$scope module priority_encoder_4to2_tb $end
$var wire 2 ! Y [1:0] $end
$var wire 1 " V $end
$var reg 4 # D [3:0] $end
$scope module uut $end
$var wire 4 $ D [3:0] $end
$var wire 1 " V $end
$var reg 2 % Y [1:0] $end
$upscope $end
$upscope $end
$enddefinitions $end
$comment Show the parameter values. $end
$dumpall
$end
#0
$dumpvars
b0 %
b0 $
b0 #
0"
b0 !
$end
#10000
1"
b1 #
b1 $
#20000
b1 !
b1 %
b10 #
b10 $
#30000
b10 !
b10 %
b100 #
b100 $
#40000
b11 !
b11 %
b1000 #
b1000 $
#50000
b1111 #
b1111 $
#80000
b10 !
b10 %
b100 #
b100 $
#90000
b0 !
b0 %
b1 #
b1 $
#100000
b11 !
b11 %
b1001 #
b1001 $
#110000
b1 !
b1 %
b11 #
b11 $
#120000
b11 !
b11 %
b1101 #
b1101 $
#140000
b10 !
b10 %
b101 #
b101 $
#150000
b1 !
b1 %
b10 #
b10 $
#160000
b0 !
b0 %
b1 #
b1 $
#170000
b11 !
b11 %
b1101 #
b1101 $
#180000
b10 !
b10 %
b110 #
b110 $
#190000
b11 !
b11 %
b1101 #
b1101 $
#210000
b1100 #
b1100 $
#220000
b1001 #
b1001 $
#230000
b10 !
b10 %
b110 #
b110 $
#240000
b101 #
b101 $
#250000
b11 !
b11 %
b1010 #
b1010 $
#260000
b10 !
b10 %
b101 #
b101 $
#270000
b111 #
b111 $
