Implementing a Boolean Function using an 8 to 1 line Multiplexer/Verilog/MUX.v

module mux (
      
    input wire [2:0] S ,
    input wire A,
    output reg Y
    );

    wire [7:0] I;

    assign I[0]= 1'b1;
    assign I[1]= 1'b1;
    assign I[2]= 1'b0;
    assign I[3]= ~A;
    assign I[4]= ~A;
    assign I[5]= 1'b0;
    assign I[6]= 1'b0;
    assign I[7]= A;

    always @(*) begin
        case (S)
            3'b000: Y = I[0];
            3'b001: Y = I[1];
            3'b010: Y = I[2];
            3'b011: Y = I[3];
            3'b100: Y = I[4];
            3'b101: Y = I[5];
            3'b110: Y = I[6]; 
            3'b111: Y = I[7];  
            default: Y = 1'b0;
        endcase

    end

endmodule

Implementing a Boolean Function using an 8 to 1 line Multiplexer/Verilog/tb.v

`timescale 1ns / 1ps

module mux_tb;
    reg [2:0] S;
    reg A;
    wire Y;
    integer i;

    mux uut(
        .S(S),
        .A(A),
        .Y(Y)
    );


    reg clk;
    initial clk =0;
    always #5 clk = ~clk;


    initial begin

        $dumpfile("waveform.vcd");
        $dumpvars(0, mux_tb);
        
        // Test for A = 0
        $display("\n\n\n=================================");
        $display("    Truth Table for A = 0 ");
        $display("=================================");
        $display(" S2   S1  S0 |  Input |  F  |");
        $display("------------------------------");
        
        A = 0;
        
        for (i = 0; i < 8; i++) begin
            S = i;
            #10; 
            $display("  %b   %b   %b  |  I%-2d   |  %b  |", S[2], S[1], S[0], i, Y);   
        end
        
        // Test for A = 1
        $display("\n\n\n=================================");
        $display("    Truth Table for A = 1 ");
        $display("=================================");
        $display(" S2   S1  S0 |  Input |  F  |");
        $display("------------------------------");
        
        A = 1;
        
        for (i = 0; i < 8; i++) begin
            S = i;
            #10; 
            $display("  %b   %b   %b  |  I%-2d   |  %b  |", S[2], S[1], S[0], i, Y);   
        end
    
        repeat (20) begin

            @(posedge clk);
                    
            S[2] = $random %2;
            S[1] = $random %2;
            S[0] = $random %2;
            A = $random %2;
            #1;
        
            $display("\n\n\n  %b  %b  %b | %b | %b", S[2], S[1], S[0], A, Y);
            
        end

        $display("\nSimulation Finished.");
        $finish;
    end

endmodule

Implementing a Boolean Function using an 8 to 1 line Multiplexer/Verilog/waveform.vcd
$date
	Tue Mar 03 22:55:50 2026
$end
$version
	Icarus Verilog
$end
$timescale
	1ps
$end
$scope module mux_tb $end
$var wire 1 ! Y $end
$var reg 1 " A $end
$var reg 3 # S [2:0] $end
$var reg 1 $ clk $end
$var integer 32 % i [31:0] $end
$scope module uut $end
$var wire 1 " A $end
$var wire 3 & S [2:0] $end
$var wire 8 ' I [7:0] $end
$var reg 1 ! Y $end
$upscope $end
$upscope $end
$enddefinitions $end
$comment Show the parameter values. $end
$dumpall
$end
#0
$dumpvars
b11011 '
b0 &
b0 %
0$
b0 #
0"
1!
$end
#5000
1$
#10000
0$
b1 #
b1 &
b1 %
#15000
1$
#20000
0!
0$
b10 #
b10 &
b10 %
#25000
1$
#30000
1!
0$
b11 #
b11 &
b11 %
#35000
1$
#40000
0$
b100 #
b100 &
b100 %
#45000
1$
#50000
0!
0$
b101 #
b101 &
b101 %
#55000
1$
#60000
0$
b110 #
b110 &
b110 %
#65000
1$
#70000
0$
b111 #
b111 &
b111 %
#75000
1$
#80000
1!
0$
b0 #
b0 &
b10000011 '
1"
b0 %
#85000
1$
#90000
0$
b1 #
b1 &
b1 %
#95000
1$
#100000
0!
0$
b10 #
b10 &
b10 %
#105000
1$
#110000
0$
b11 #
b11 &
b11 %
#115000
1$
#120000
0$
b100 #
b100 &
b100 %
#125000
1$
#130000
0$
b101 #
b101 &
b101 %
#135000
1$
#140000
0$
b110 #
b110 &
b110 %
#145000
1$
#150000
1!
0$
b111 #
b111 &
b111 %
#155000
1$
#160000
0$
b1000 %
#165000
0!
b11 #
b11 &
1$
#170000
0$
#175000
b11011 '
0"
b111 #
b111 &
1$
#180000
0$
#185000
b10000011 '
1"
b110 #
b110 &
1$
#190000
0$
#195000
b11011 '
0"
b101 #
b101 &
1$
#200000
0$
#205000
b10000011 '
1"
1$
#210000
0$
#215000
b11011 '
0"
b10 #
b10 &
1$
#220000
0$
#225000
b10000011 '
1"
1$
#230000
0$
#235000
b11011 '
0"
b111 #
b111 &
1$
#240000
0$
#245000
1!
b10000011 '
1"
b0 #
b0 &
1$
#250000
0$
#255000
0!
b11 #
b11 &
1$
#260000
0$
#265000
b11011 '
0"
b110 #
b110 &
1$
#270000
0$
#275000
b111 #
b111 &
1$
#280000
0$
#285000
1!
b0 #
b0 &
1$
#290000
0$
#295000
0!
b10000011 '
1"
b100 #
b100 &
1$
#300000
0$
#305000
1!
b11011 '
0"
1$
#310000
0$
#315000
b10000011 '
1"
b1 #
b1 &
1$
#320000
0$
#325000
0!
b11011 '
0"
b111 #
b111 &
1$
#330000
0$
#335000
0!
b10000011 '
1"
b11 #
b11 &
1$
#340000
0$
#345000
1!
b1 #
b1 &
1$
#350000
0$
#355000
1!
b11011 '
0"
b11 #
b11 &
1$
