D-type Flip Flop/d_type/verilog/d_type.v

`timescale 1ns/1ps

module d_type (
input wire clk,
input wire d,
input pr,
input cr, 
output wire q,
output wire q_bar );

wire d_bar, clk_bar;
wire bc,cd,ef,gh, ij,kl;   

not #1 one (d_bar, d);
not #1 two (clk_bar, clk);

nand #1 three (bc, d, clk, q_bar);
nand #1 four (cd, d_bar, clk, q);

nand #1 five (ef, pr, bc, gh);
nand #1 six (gh, cd, cr, ef);

nand #1 seven (ij, ef, clk_bar);
nand #1 eight (kl, gh, clk_bar);

nand #1 nine (q, q_bar, ij);
nand #1 ten (q_bar, kl, q);

endmodule

D-type Flip Flop/d_type/verilog/tb_d_type.v
`timescale 1ns/1ps

module d_type_tb;

    reg clk, d, pr, cr;
    wire q, q_bar;

    d_type dut (
        .clk(clk), .d(d), .pr(pr), .cr(cr),
        .q(q), .q_bar(q_bar)
    );

    initial clk = 0;
    always #5 clk = ~clk;

    initial begin
        $dumpfile("d_type_tb.vcd");
        $dumpvars(0, d_type_tb);

        d = 0;

        pr = 1; cr = 1; #10;   // normal
        pr = 0; cr = 1; #10;   // preset
        pr = 1; cr = 0; #10;   // clear
        pr = 1; cr = 1; #10;   // back to normal

        repeat (10) begin
            d = $random;
            #10;
        end

        #10 $finish;
    end

endmodule

D-type Flip Flop/d_type/verilog/d_type_tb.vcd
$date
	Wed Sep 16 23:20:31 2026
$end
$version
	Icarus Verilog
$end
$timescale
	1ps
$end
$scope module d_type_tb $end
$var wire 1 ! q_bar $end
$var wire 1 " q $end
$var reg 1 # clk $end
$var reg 1 $ cr $end
$var reg 1 % d $end
$var reg 1 & pr $end
$scope module dut $end
$var wire 1 ' bc $end
$var wire 1 ( cd $end
$var wire 1 # clk $end
$var wire 1 ) clk_bar $end
$var wire 1 $ cr $end
$var wire 1 % d $end
$var wire 1 * d_bar $end
$var wire 1 + ef $end
$var wire 1 , gh $end
$var wire 1 - ij $end
$var wire 1 . kl $end
$var wire 1 & pr $end
$var wire 1 " q $end
$var wire 1 ! q_bar $end
$upscope $end
$upscope $end
$enddefinitions $end
$comment Show the parameter values. $end
$dumpall
$end
#0
$dumpvars
x.
x-
x,
x+
x*
x)
x(
x'
1&
0%
1$
0#
x"
x!
$end
#1000
1*
1)
1(
1'
#5000
1#
#6000
0)
x(
#7000
1-
1.
#10000
0#
0&
#11000
1)
1(
1+
#12000
x.
0,
0-
#13000
1.
1"
#14000
0!
#15000
1#
#16000
0)
0(
#17000
1-
1,
#20000
0#
0$
1&
#21000
1)
1(
0+
#22000
0.
#23000
1!
#24000
0"
#25000
1#
#26000
0)
#27000
1.
#30000
0#
1$
#31000
1)
#32000
0.
#35000
1#
#36000
0)
#37000
1.
#40000
0#
#41000
1)
#42000
0.
#45000
1#
#46000
0)
#47000
1.
#50000
0#
1%
#51000
1)
0*
#52000
0.
#55000
1#
#56000
0)
0'
#57000
1.
1+
#58000
0,
#60000
0#
#61000
1)
1'
#62000
0-
#63000
1"
#64000
0!
#65000
1#
#66000
0)
#67000
1-
#70000
0#
#71000
1)
#72000
0-
#75000
1#
#76000
0)
#77000
1-
#80000
0#
#81000
1)
#82000
0-
#85000
1#
#86000
0)
#87000
1-
#90000
0#
#91000
1)
#92000
0-
#95000
1#
#96000
0)
#97000
1-
#100000
0#
#101000
1)
#102000
0-
#105000
1#
#106000
0)
#107000
1-
#110000
0#
0%
#111000
1)
1*
#112000
0-
#115000
1#
#116000
0)
0(
#117000
1-
1,
#118000
0+
#120000
0#
1%
#121000
1)
1(
0*
#122000
0.
#123000
1!
#124000
0"
#125000
1#
#126000
0)
0'
#127000
1.
1+
#128000
0,
#130000
0#
#131000
1)
1'
#132000
0-
#133000
1"
#134000
0!
#135000
1#
#136000
0)
#137000
1-
#140000
0#
#141000
1)
#142000
0-
#145000
1#
#146000
0)
#147000
1-
