Basic Logic Gates/Verilog/NOR GATE/nor.v
module nor_gate (
    input A,
    input B,
    output X,
    output Y,
    output Z
);
wire a,b,c;

assign X = ~(A | A); // NOT gate

assign a = ~(A | B); 
assign Y = ~(a | a); // AND gate

assign b = ~(A | A);
assign c =~(B | B);
assign Z = ~(b | c); // OR gate

endmodule

Basic Logic Gates/Verilog/NOR GATE/nor_tb.v
`timescale 1ns / 1ps
module nor_gate_tb;
 
 reg A,B;
 wire X,Y,Z;

 nor_gate uut (
    .A(A),
    .B(B),
    .X(X),
    .Y(Y),
    .Z(Z)
 );
 initial begin 
 $dumpfile("wave.vcd");
 $dumpvars(0, nor_gate_tb);
 end

 reg clk;
 initial clk = 0;
 always #5 clk = ~clk;

 always @(posedge clk) begin
 A <= $random & 1'b1;
 B <= $random & 1'b1;
 end    

 initial begin
    #100 $finish;
    end

endmodule

Basic Logic Gates/Verilog/NOR GATE/wave.vcd
$date
	Wed Jan 14 19:29:51 2026
$end
$version
	Icarus Verilog
$end
$timescale
	1ps
$end
$scope module nor_gate_tb $end
$var wire 1 ! Z $end
$var wire 1 " Y $end
$var wire 1 # X $end
$var reg 1 $ A $end
$var reg 1 % B $end
$var reg 1 & clk $end
$scope module uut $end
$var wire 1 $ A $end
$var wire 1 % B $end
$var wire 1 # X $end
$var wire 1 " Y $end
$var wire 1 ! Z $end
$var wire 1 ' a $end
$var wire 1 ( b $end
$var wire 1 ) c $end
$upscope $end
$upscope $end
$enddefinitions $end
$comment Show the parameter values. $end
$dumpall
$end
#0
$dumpvars
x)
x(
x'
0&
x%
x$
x#
x"
x!
$end
#5000
1"
0!
0)
1#
0'
1(
1%
0$
1&
#10000
0&
#15000
1!
0#
0(
1$
1&
#20000
0&
#25000
1&
#30000
0&
#35000
0!
1)
0%
1&
#40000
0&
#45000
1!
0)
1%
1&
#50000
0&
#55000
0!
1#
1(
0$
1&
#60000
0&
#65000
1)
0#
0(
0%
1$
1&
#70000
0&
#75000
1&
#80000
0&
#85000
1&
#90000
0&
#95000
1!
0)
1%
1&
