Adder and Subtractor/Verilog/Subtractor/subtractor.v
module subtractor (
    input A, B, C,              // Bin = Borrow in
    output diff_half, borrow_half,
    output diff_full, borrow_full
);

    // Half Subtractor
    assign diff_half = A ^ B;          // Difference
    assign borrow_half = ~A & B;       // Borrow

    // Full Subtractor
    assign diff_full = A ^ B ^ C;    // Difference
    assign borrow_full = (~A & B) | ((~A | B) & C); // Borrow out

endmodule

Adder and Subtractor/Verilog/Subtractor/tb.v
`timescale 1ns / 1ps
module subtractor_tb;

    // Inputs
    reg A, B, C;

    // Outputs
    wire diff_half, borrow_half;
    wire diff_full, borrow_full;

    // Clock
    reg clk;

    // Instantiate DUT
    subtractor uut (
        .A(A),
        .B(B),
        .C(C),
        .diff_half(diff_half),
        .borrow_half(borrow_half),
        .diff_full(diff_full),
        .borrow_full(borrow_full)
    );

    // Clock generation for random inputs
    initial clk = 0;
    always #5 clk = ~clk;

    // Dump waveform for GTKWave from the start
    initial begin
        $dumpfile("waveform.vcd");
        $dumpvars(0, subtractor_tb);
    end

    // --------------------------
    // Part 1: Manual test vectors
    // --------------------------
    initial begin
        C = 0;

        $display("---- Half Subtractor ---");
        $display("A B | diffH borrowH");
        A=0; B=0; #10; $display("%b %b | %b %b", A,B,diff_half,borrow_half);
        A=0; B=1; #10; $display("%b %b | %b %b", A,B,diff_half,borrow_half);
        A=1; B=0; #10; $display("%b %b | %b %b", A,B,diff_half,borrow_half);
        A=1; B=1; #10; $display("%b %b | %b %b", A,B,diff_half,borrow_half);

        $display("\n---- Full Subtractor ----");
        $display("A B C | diffH borrowH | diffF borrowF");
        A=0; B=0; C=0; #10; $display("%b %b %b | %b %b | %b %b", A,B,C,diff_half,borrow_half,diff_full,borrow_full);
        A=0; B=0; C=1; #10; $display("%b %b %b | %b %b | %b %b", A,B,C,diff_half,borrow_half,diff_full,borrow_full);
        A=0; B=1; C=0; #10; $display("%b %b %b | %b %b | %b %b", A,B,C,diff_half,borrow_half,diff_full,borrow_full);
        A=0; B=1; C=1; #10; $display("%b %b %b | %b %b | %b %b", A,B,C,diff_half,borrow_half,diff_full,borrow_full);
        A=1; B=0; C=0; #10; $display("%b %b %b | %b %b | %b %b", A,B,C,diff_half,borrow_half,diff_full,borrow_full);
        A=1; B=0; C=1; #10; $display("%b %b %b | %b %b | %b %b", A,B,C,diff_half,borrow_half,diff_full,borrow_full);
        A=1; B=1; C=0; #10; $display("%b %b %b | %b %b | %b %b", A,B,C,diff_half,borrow_half,diff_full,borrow_full);
        A=1; B=1; C=1; #10; $display("%b %b %b | %b %b | %b %b", A,B,C,diff_half,borrow_half,diff_full,borrow_full);
    end

    // --------------------------
    // Part 2: Random inputs
    // --------------------------
    // Only after the manual vectors (delay to avoid overlap)
    initial begin
        #100; // wait for manual vectors to finish
        forever @(posedge clk) begin
            A <= $random & 1;
            B <= $random & 1;
            C <= $random & 1;
        end
    end



    // Stop simulation after enough time for both parts
    initial begin
        #300 $finish;
    end

endmodule

Adder and Subtractor/Verilog/Subtractor/waveform.vcd
$date
	Sat Feb 07 02:14:34 2026
$end
$version
	Icarus Verilog
$end
$timescale
	1ps
$end
$scope module subtractor_tb $end
$var wire 1 ! diff_half $end
$var wire 1 " diff_full $end
$var wire 1 # borrow_half $end
$var wire 1 $ borrow_full $end
$var reg 1 % A $end
$var reg 1 & B $end
$var reg 1 ' C $end
$var reg 1 ( clk $end
$scope module uut $end
$var wire 1 % A $end
$var wire 1 & B $end
$var wire 1 ' C $end
$var wire 1 $ borrow_full $end
$var wire 1 # borrow_half $end
$var wire 1 " diff_full $end
$var wire 1 ! diff_half $end
$upscope $end
$upscope $end
$enddefinitions $end
$comment Show the parameter values. $end
$dumpall
$end
#0
$dumpvars
0(
0'
0&
0%
0$
0#
0"
0!
$end
#5000
1(
#10000
1"
1$
1!
1#
0(
1&
#15000
1(
#20000
0$
0#
0(
0&
1%
#25000
1(
#30000
0"
0!
0(
1&
#35000
1(
#40000
0(
0&
0%
#45000
1(
#50000
1$
1"
0(
1'
#55000
1(
#60000
1!
1#
0(
0'
1&
#65000
1(
#70000
0"
0(
1'
#75000
1(
#80000
0$
1"
0#
0(
0'
0&
1%
#85000
1(
#90000
0"
0(
1'
#95000
1(
#100000
0!
0(
0'
1&
#105000
1$
1#
1!
1'
0%
1(
#110000
0#
1"
0!
0(
1%
#115000
1(
#120000
0(
#125000
0$
0"
1!
0&
1(
#130000
0(
#135000
1(
#140000
0(
#145000
1(
#150000
0(
#155000
1$
1"
1#
0'
1&
0%
1(
#160000
0(
#165000
0$
0#
0"
0!
1%
1(
#170000
0(
#175000
1"
1!
0&
1(
#180000
0(
#185000
1$
1#
1&
0%
1(
#190000
0(
#195000
0#
0!
1'
1%
1(
#200000
0(
#205000
0$
1!
0'
0&
1(
#210000
0(
#215000
1$
0!
1'
0%
1(
#220000
0(
#225000
0"
1!
1#
1&
1(
#230000
0(
#235000
0#
1"
0!
1%
1(
#240000
0(
#245000
0&
0%
1(
#250000
0(
#255000
0$
0"
0'
1&
1%
1(
#260000
0(
#265000
0&
0%
1(
#270000
0(
#275000
1"
1$
1!
1#
1&
1(
#280000
0(
#285000
0"
1'
1(
#290000
0(
#295000
0$
0!
0#
0'
0&
1(
